LICENSE
MANIFEST.in
README.md
requirements.txt
setup.cfg
setup.py
django_mp_trans.egg-info/PKG-INFO
django_mp_trans.egg-info/SOURCES.txt
django_mp_trans.egg-info/dependency_links.txt
django_mp_trans.egg-info/requires.txt
django_mp_trans.egg-info/top_level.txt
trans/__init__.py
trans/admin.py
trans/forms.py
trans/urls.py
trans/views.py
trans/templates/trans/admin/change_form.html