Metadata-Version: 1.1
Name: django-mp-trans
Version: 1.1
Summary: Django trans apps
Home-page: https://github.com/pmaigutyak/mp-trans
Author: Paul Maigutyak
Author-email: pmaigutyak@gmail.com
License: MIT
Download-URL: https://github.com/pmaigutyak/mp-trans/archive/1.1.tar.gz
Platform: UNKNOWN
